hippocampai/__init__.py
hippocampai/async_client.py
hippocampai/client.py
hippocampai/client_extensions.py
hippocampai/config.py
hippocampai/scheduler.py
hippocampai/setup_app.py
hippocampai/telemetry.py
hippocampai/__pycache__/retrieval/__init__.py
hippocampai/__pycache__/retrieval/bm25.py
hippocampai/__pycache__/retrieval/rerank.py
hippocampai/__pycache__/retrieval/retriever.py
hippocampai/__pycache__/retrieval/router.py
hippocampai/__pycache__/retrieval/rrf.py
hippocampai/adapters/__init__.py
hippocampai/adapters/llm_base.py
hippocampai/adapters/provider_ollama.py
hippocampai/adapters/provider_openai.py
hippocampai/api/__init__.py
hippocampai/api/app.py
hippocampai/api/deps.py
hippocampai/cli/__init__.py
hippocampai/cli/main.py
hippocampai/embed/__init__.py
hippocampai/embed/embedder.py
hippocampai/graph/__init__.py
hippocampai/graph/memory_graph.py
hippocampai/jobs/__init__.py
hippocampai/jobs/scheduler.py
hippocampai/models/__init__.py
hippocampai/models/memory.py
hippocampai/pipeline/__init__.py
hippocampai/pipeline/consolidate.py
hippocampai/pipeline/dedup.py
hippocampai/pipeline/extractor.py
hippocampai/pipeline/importance.py
hippocampai/retrieval/__init__.py
hippocampai/retrieval/bm25.py
hippocampai/retrieval/rerank.py
hippocampai/retrieval/retriever.py
hippocampai/retrieval/router.py
hippocampai/retrieval/rrf.py
hippocampai/storage/__init__.py
hippocampai/storage/kv_store.py
hippocampai/utils/__init__.py
hippocampai/utils/cache.py
hippocampai/utils/context_injection.py
hippocampai/utils/retry.py
hippocampai/utils/scoring.py
hippocampai/utils/structured_logging.py
hippocampai/utils/time.py
hippocampai/vector/__init__.py
hippocampai/vector/qdrant_store.py
hippocampai/versioning/__init__.py
hippocampai/versioning/memory_versioning.py
hippocampai-1.0.0.dist-info/licenses/LICENSE
hippocampai-1.0.0.dist-info/METADATA
hippocampai-1.0.0.dist-info/WHEEL
hippocampai-1.0.0.dist-info/entry_points.txt
hippocampai-1.0.0.dist-info/top_level.txt
hippocampai-1.0.0.dist-info/RECORD
