Metadata-Version: 2.4
Name: hippocampai
Version: 1.0.0
Summary: HippocampAI — autonomous long-term memory engine with hybrid retrieval and cross-encoder reranking
Author: HippocampAI Contributors
Author-email: Rex Divakar <rexdivakar@hotmail.com>
Maintainer-email: Rex Divakar <rexdivakar@hotmail.com>
License-Expression: Apache-2.0
Project-URL: Homepage, https://github.com/rexdivakar/HippocampAI
Project-URL: Documentation, https://github.com/rexdivakar/HippocampAI#readme
Project-URL: Repository, https://github.com/rexdivakar/HippocampAI
Project-URL: Issue Tracker, https://github.com/rexdivakar/HippocampAI/issues
Project-URL: Changelog, https://github.com/rexdivakar/HippocampAI/blob/main/CHANGELOG.md
Keywords: llm,memory,rag,retrieval,vector-database,qdrant,ai,embeddings,semantic-search
Classifier: Development Status :: 4 - Beta
Classifier: Intended Audience :: Developers
Classifier: Intended Audience :: Science/Research
Classifier: Operating System :: OS Independent
Classifier: Programming Language :: Python :: 3
Classifier: Programming Language :: Python :: 3.9
Classifier: Programming Language :: Python :: 3.10
Classifier: Programming Language :: Python :: 3.11
Classifier: Programming Language :: Python :: 3.12
Classifier: Topic :: Scientific/Engineering :: Artificial Intelligence
Classifier: Topic :: Software Development :: Libraries :: Python Modules
Requires-Python: >=3.9
License-File: LICENSE
Requires-Dist: pydantic<3.0,>=2.6
Requires-Dist: pydantic-settings<3.0,>=2.0
Requires-Dist: python-dotenv<2.0,>=1.0
Requires-Dist: httpx<1.0,>=0.25
Requires-Dist: apscheduler<4.0,>=3.10
Requires-Dist: cachetools<6.0,>=5.3
Requires-Dist: qdrant-client<2.0,>=1.7
Requires-Dist: rank-bm25<1.0,>=0.2
Requires-Dist: sentence-transformers<3.0,>=2.2
Requires-Dist: typer[all]<1.0,>=0.9
Requires-Dist: tenacity<9.0,>=8.2
Requires-Dist: python-json-logger<3.0,>=2.0
Provides-Extra: all
Requires-Dist: anthropic<1.0,>=0.39; extra == "all"
Requires-Dist: groq<1.0,>=0.4; extra == "all"
Requires-Dist: ollama<1.0,>=0.3; extra == "all"
Requires-Dist: openai<2.0,>=1.0; extra == "all"
Requires-Dist: fastapi<1.0,>=0.110; extra == "all"
Requires-Dist: uvicorn[standard]<1.0,>=0.24; extra == "all"
Requires-Dist: flask<4.0,>=3.0; extra == "all"
Requires-Dist: flask-cors<5.0,>=4.0; extra == "all"
Provides-Extra: api
Requires-Dist: fastapi<1.0,>=0.110; extra == "api"
Requires-Dist: uvicorn[standard]<1.0,>=0.24; extra == "api"
Provides-Extra: web
Requires-Dist: flask<4.0,>=3.0; extra == "web"
Requires-Dist: flask-cors<5.0,>=4.0; extra == "web"
Provides-Extra: ollama
Requires-Dist: ollama<1.0,>=0.3; extra == "ollama"
Provides-Extra: openai
Requires-Dist: openai<2.0,>=1.0; extra == "openai"
Provides-Extra: anthropic
Requires-Dist: anthropic<1.0,>=0.39; extra == "anthropic"
Provides-Extra: groq
Requires-Dist: groq<1.0,>=0.4; extra == "groq"
Provides-Extra: dev
Requires-Dist: black<25.0,>=24.4; extra == "dev"
Requires-Dist: bandit[toml]<2.0,>=1.7; extra == "dev"
Requires-Dist: liccheck<1.0,>=0.7; extra == "dev"
Requires-Dist: mypy<2.0,>=1.8; extra == "dev"
Requires-Dist: pip-audit<3.0,>=2.7; extra == "dev"
Requires-Dist: pre-commit<4.0,>=3.5; extra == "dev"
Requires-Dist: pytest<8.0,>=7.4; extra == "dev"
Requires-Dist: pytest-asyncio<0.23,>=0.21; extra == "dev"
Requires-Dist: pytest-cov<5.0,>=4.1; extra == "dev"
Requires-Dist: ruff<1.0,>=0.3; extra == "dev"
Requires-Dist: safety<3.0,>=2.3; extra == "dev"
Provides-Extra: test
Requires-Dist: pytest<8.0,>=7.4; extra == "test"
Requires-Dist: pytest-asyncio<0.23,>=0.21; extra == "test"
Requires-Dist: pytest-cov<5.0,>=4.1; extra == "test"
Provides-Extra: docs
Requires-Dist: mkdocs<2.0,>=1.5; extra == "docs"
Requires-Dist: mkdocs-material<10.0,>=9.5; extra == "docs"
Requires-Dist: mkdocstrings[python]<1.0,>=0.24; extra == "docs"
Dynamic: license-file
